configurer/__init__.py
configurer/main.py
configurer/core/__init__.py
configurer/core/loader.py
configurer/utils/__init__.py
configurer/utils/helpers.py
configurer-0.2.0.dist-info/METADATA
configurer-0.2.0.dist-info/WHEEL
configurer-0.2.0.dist-info/licenses/LICENSE
configurer-0.2.0.dist-info/RECORD
