Metadata-Version: 2.3
Name: configurer
Version: 0.2.0
Summary: A dynamic configuration loader for Python applications
Project-URL: Homepage, https://github.com/lcances/config_loader
Project-URL: Documentation, https://github.com/lcances/config_loader#readme
Project-URL: Repository, https://github.com/lcances/config_loader.git
Project-URL: Bug Tracker, https://github.com/lcances/config_loader/issues
Author-email: Leo Cances <leocances@gmail.com>
License: MIT License
License-File: LICENSE
Classifier: Development Status :: 3 - Alpha
Classifier: Intended Audience :: Developers
Classifier: License :: OSI Approved :: MIT License
Classifier: Programming Language :: Python :: 3
Classifier: Programming Language :: Python :: 3.8
Classifier: Programming Language :: Python :: 3.9
Classifier: Programming Language :: Python :: 3.10
Classifier: Programming Language :: Python :: 3.11
Requires-Python: >=3.8
Requires-Dist: pyyaml>=6.0
Provides-Extra: test
Requires-Dist: pytest>=7.0; extra == 'test'
